tephi/__init__.py
tephi/_constants.py
tephi/artists.py
tephi/constants.py
tephi/demo.py
tephi/isopleths.py
tephi/transforms.py
tephi/etc/test_data/barbs.txt
tephi/etc/test_data/comma_sep.txt
tephi/etc/test_data/dews.txt
tephi/etc/test_data/temps.txt
tephi/tests/__init__.py
tephi/tests/conftest.py
tephi/tests/idiff.py
tephi/tests/test_imagerepo.py
tephi/tests/test_tephigram.py
tephi/tests/results/barbs.npz
tephi/tests/results/dews.npz
tephi/tests/results/imagerepo.json
tephi/tests/results/temps.npz
tephi-0.4.0.post0.dist-info/licenses/LICENSE
tephi-0.4.0.post0.dist-info/METADATA
tephi-0.4.0.post0.dist-info/WHEEL
tephi-0.4.0.post0.dist-info/top_level.txt
tephi-0.4.0.post0.dist-info/RECORD
