Metadata-Version: 2.4
Name: tephi
Version: 0.4.0.post0
Summary: Tephigram plotting in Python
Author-email: Tephi Contributors <scitools.pub@gmail.com>
License-Expression: BSD-3-Clause
Project-URL: Code, https://github.com/SciTools/tephi
Project-URL: Issues, https://github.com/SciTools/tephi/issues
Project-URL: Binder, https://mybinder.org/v2/gh/SciTools/tephi/main?filepath=index.ipynb
Project-URL: Docs, https://tephi.readthedocs.io/en/latest/
Keywords: tephigram,radiosonde,meteorology,visualization
Classifier: Development Status :: 4 - Beta
Classifier: Intended Audience :: Science/Research
Classifier: Operating System :: OS Independent
Classifier: Programming Language :: Python
Classifier: Programming Language :: Python :: 3
Classifier: Programming Language :: Python :: 3.10
Classifier: Programming Language :: Python :: 3.11
Classifier: Topic :: Scientific/Engineering :: Atmospheric Science
Classifier: Topic :: Scientific/Engineering :: Visualization
Requires-Python: >=3.10
License-File: LICENSE
Requires-Dist: matplotlib
Requires-Dist: numpy
Requires-Dist: scipy
Requires-Dist: shapely
Dynamic: license-file
